constants.vh
//-- Blocks to read
`define IDLE            4'h0
`define ETH_DEST_ADDR   4'h1
`define ETH_SRC_ADDR    4'h2
`define FRAME_TYPE      4'h3
`define HW_TYPE         4'h4
`define PROT_TYPE       4'h5
`define HW_LEN          4'h6
`define PROT_LEN        4'h7
`define ARP_OP          4'h8
`define ARP_SRC_ADDR    4'h9
`define ARP_SRC_IP      4'hA
`define ARP_DEST_ADDR   4'hB
`define ARP_DEST_IP     4'hC
`define END             4'hD


//-- frame values
`define BRDCAST_DEST_ADDR  48'hFFFFFFFFFFFF
`define ARP_FRAME_TYPE     16'h0806
`define ETH_HW_TYPE        16'h0001
`define IP_PROT_TYPE       16'h0800
`define ETH_HW_LEN         8'h06
`define IP_PROT_LEN        8'h04
`define REQ_ARP_OP         16'h0001
`define REP_ARP_OP         16'h0002
`define ARP_REQ_ADDR       48'h000000000000

blk_next_state.v
//================================================================
// \ \/ /  _ \  |_   _| __ __ _  __| (_)_ __   __ _  
//  \  /| |_) |   | || '__/ _` |/ _` | | '_ \ / _` | 
//  /  \|  _ <    | || | | (_| | (_| | | | | | (_| | 
// /_/\_\_| \_\   |_||_|  \__,_|\__,_|_|_| |_|\__, | 
//                                            |___/  
//  _____ ____   ____    _     ____            _           _   
// |  ___|  _ \ / ___|  / \    |  _ \ _ __ ___ (_) ___  ___| |_ 
// | |_  | |_) | |  _  / _ \   | |_) | '__/ _ \| |/ _ \/ __| __|
// |  _| |  __/| |_| |/ ___ \  |  __/| | | (_) | |  __/ (__| |_ 
// |_|   |_|    \____/_/   \_\ |_|   |_|  \___// |\___|\___|\__|
//                                           |__/              
//Leela Pakanati
//Block next state module
//
//This is a module that is able to parse the next state
//from the current state and number of blocks counted
//================================================================

`include "constants.vh"

module blk_next_state(
    input wire       clk,
    input wire       areset,
    input wire [3:0] state,
    input wire       start,
    input wire       ack,

    output reg [2:0] blk_cnt,
    output reg [3:0] next_state
);

    // Determine Next state Logic
    always @(areset, state, blk_cnt, start) begin
        if(areset)
            next_state  <= 4'h0;
        else
            case(state)
                `IDLE:
                     if(start) next_state <= `ETH_DEST_ADDR; else next_state <= `IDLE;
                `ETH_DEST_ADDR:
                     if(blk_cnt == 3'h5) next_state <= `ETH_SRC_ADDR; else next_state <= `ETH_DEST_ADDR;
                `ETH_SRC_ADDR:
                     if(blk_cnt == 3'h5) next_state <= `FRAME_TYPE; else next_state <= `ETH_SRC_ADDR;
                `FRAME_TYPE:
                     if(blk_cnt == 3'h1) next_state <= `HW_TYPE; else next_state <= `FRAME_TYPE;
                `HW_TYPE:
                     if(blk_cnt == 3'h1) next_state <= `PROT_TYPE; else next_state <= `HW_TYPE;
                `PROT_TYPE:
                     if(blk_cnt == 3'h1) next_state <= `HW_LEN; else next_state <= `PROT_TYPE;
                `HW_LEN:
                     next_state <= `PROT_LEN;
                `PROT_LEN:
                     next_state <= `ARP_OP;
                `ARP_OP:
                     if(blk_cnt == 3'h1) next_state <= `ARP_SRC_ADDR; else next_state <= `ARP_OP;
                `ARP_SRC_ADDR:
                     if(blk_cnt == 3'h5) next_state <= `ARP_SRC_IP; else next_state <= `ARP_SRC_ADDR;
                `ARP_SRC_IP:
                     if(blk_cnt == 3'h3) next_state <= `ARP_DEST_ADDR; else next_state <= `ARP_SRC_IP;
                `ARP_DEST_ADDR:
                     if(blk_cnt == 3'h5) next_state <= `ARP_DEST_IP; else next_state <= `ARP_DEST_ADDR;
                `ARP_DEST_IP:
                     if(blk_cnt == 3'h3) next_state <= `END; else next_state <= `ARP_DEST_IP;
                `END:
                    if(!start) next_state <= `IDLE; else next_state <= `END;
                default:
                    next_state <= `IDLE;
            endcase
    end

    //-- Block Count logic
    always @(posedge clk or areset) begin
        if(areset)
            blk_cnt <= 4'h0;
        else begin
            //-- for sending, on first sending block, don't increment blk_cnt
            //-- until ack is registered as high
            if ((state == `ETH_DEST_ADDR) && (blk_cnt == 0))
                if(ack)
                    blk_cnt <= blk_cnt + 1;
                else
                    blk_cnt <= 4'h0;

            else if ((state == `IDLE) || (state == `END))
                blk_cnt <= 4'h0;

            else
                //-- if states remains the same, then count up, else reset to 0
                if (state == next_state)
                    blk_cnt <= blk_cnt + 1;
                else
                    blk_cnt <= 4'h0;
        end
    end
endmodule

output_MAC.v
//================================================================
// \ \/ /  _ \  |_   _| __ __ _  __| (_)_ __   __ _  
//  \  /| |_) |   | || '__/ _` |/ _` | | '_ \ / _` | 
//  /  \|  _ <    | || | | (_| | (_| | | | | | (_| | 
// /_/\_\_| \_\   |_||_|  \__,_|\__,_|_|_| |_|\__, | 
//                                            |___/  
//  _____ ____   ____    _     ____            _           _   
// |  ___|  _ \ / ___|  / \    |  _ \ _ __ ___ (_) ___  ___| |_ 
// | |_  | |_) | |  _  / _ \   | |_) | '__/ _ \| |/ _ \/ __| __|
// |  _| |  __/| |_| |/ ___ \  |  __/| | | (_) | |  __/ (__| |_ 
// |_|   |_|    \____/_/   \_\ |_|   |_|  \___// |\___|\___|\__|
//                                           |__/              
//Leela Pakanati
//Input Detect Module
//
//This is a module that sends the MAC address of a device over 
//the IPv4 layer
//================================================================

`include "constants.vh"

module output_MAC(
    input wire          clk,
    input wire          areset,

    output reg          data_valid,
    output reg [7:0]    data_tx,
    input wire          data_ack_tx,

    input wire          send_mac,
    input wire [47:0]   source_mac,
    input wire [31:0]   source_ip,
    input wire [47:0]   my_mac,
    input wire [31:0]   my_ip
);

    reg [3:0] state;
    wire [3:0] next_state;
    wire [2:0] blk_cnt;
    
    //get next state
    blk_next_state bns(
        .clk(clk),
        .areset(areset),
        .state(state),
        .start(send_mac),
        .ack(data_ack_tx),

        .blk_cnt(blk_cnt),
        .next_state(next_state)
    );
 
    //-- State Sequential logic
    always @(posedge clk or areset) begin
        if(areset)
            state <= `IDLE;
        else
            state <= next_state;
    end

    //-- output based on state
    always @(posedge clk or areset) begin
        if (areset) begin
            data_valid  <= 1'b0;
            data_tx     <= 8'h0;
        end else begin
            if ((state == `IDLE) || (state == `END))
                data_valid      <= 1'b0;
            else
                data_valid      <= 1'b1;


            case(state)
                //-- shift in each value of blk_cnt*8 (>>3)
                `ETH_DEST_ADDR:
                    data_tx     <= (source_mac >> ((5-blk_cnt)*8));

                `ETH_SRC_ADDR:
                    data_tx     <= (my_mac >> ((5-blk_cnt)*8));

                `FRAME_TYPE:
                    data_tx     <= (`ARP_FRAME_TYPE >> ((1-blk_cnt)*8));

                `HW_TYPE:
                    data_tx     <= (`ETH_HW_TYPE >> ((1-blk_cnt)*8));
                                    
                `PROT_TYPE:
                    data_tx     <= (`IP_PROT_TYPE >> ((1-blk_cnt)*8));

                `HW_LEN:
                    data_tx     <= (`ETH_HW_LEN >> (blk_cnt*8));

                `PROT_LEN:
                    data_tx     <= (`IP_PROT_LEN >> (blk_cnt*8));

                `ARP_OP:
                    data_tx     <= (`REP_ARP_OP >> ((1-blk_cnt)*8));

                `ARP_SRC_ADDR:
                    data_tx     <= (my_mac >> ((5-blk_cnt)*8));

                `ARP_SRC_IP:
                    data_tx     <= (my_ip >> ((3-blk_cnt)*8));

                `ARP_DEST_ADDR:
                    data_tx     <= (source_mac >> ((5-blk_cnt)*8));

                `ARP_DEST_IP:
                    data_tx     <= (source_ip >> ((3-blk_cnt)*8));

                default:
                    data_tx     <= 8'h00;

            endcase
        end
    end
endmodule

input_det.v
//================================================================
// \ \/ /  _ \  |_   _| __ __ _  __| (_)_ __   __ _  
//  \  /| |_) |   | || '__/ _` |/ _` | | '_ \ / _` | 
//  /  \|  _ <    | || | | (_| | (_| | | | | | (_| | 
// /_/\_\_| \_\   |_||_|  \__,_|\__,_|_|_| |_|\__, | 
//                                            |___/  
//  _____ ____   ____    _     ____            _           _   
// |  ___|  _ \ / ___|  / \    |  _ \ _ __ ___ (_) ___  ___| |_ 
// | |_  | |_) | |  _  / _ \   | |_) | '__/ _ \| |/ _ \/ __| __|
// |  _| |  __/| |_| |/ ___ \  |  __/| | | (_) | |  __/ (__| |_ 
// |_|   |_|    \____/_/   \_\ |_|   |_|  \___// |\___|\___|\__|
//                                           |__/              
//Leela Pakanati
//Input Detect Module
//
//This is a module that recognizes a ARP request corresponding
//to its IP Address 
//================================================================

`include "constants.vh"

module input_det(
    input wire          clk,
    input wire          areset,
    input wire [31:0]   my_ip,
    input wire          data_valid,
    input wire [7:0]    data_rx,

    output reg          arp_send,
    output reg [47:0]   source_mac,
    output reg [31:0]   source_ip
);


    reg [3:0] state;
    wire [3:0] next_state;
    wire [2:0] blk_cnt; 

    reg [47:0] eth_dest_addr;
    reg [47:0] eth_src_addr;
    reg [15:0] frame_type;
    reg [15:0] hw_type;
    reg [15:0] prot_type;
    reg [7:0]  hw_len;
    reg [7:0]  prot_len;
    reg [15:0] arp_op;
    reg [47:0] arp_src_addr;
    reg [31:0] arp_src_ip;
    reg [47:0] arp_dest_addr;
    reg [31:0] arp_dest_ip;

    //-- State Sequential logic
    always @(posedge clk or areset) begin
        if(areset) begin
            //if currently reading a byte go to state END
            //else go to IDLE
            if (data_valid) state <= `END; else state <= `IDLE;
        end else state <= next_state;
    end

    //get next state
    blk_next_state bns(
        .clk(clk),
        .areset(areset),
        .state(state),
        .start(data_valid),
        .ack(1'b1),

        .blk_cnt(blk_cnt),
        .next_state(next_state)
    );


    //-- store data
    always @(state, blk_cnt or areset) begin
        if (areset) begin
            eth_dest_addr   <= 48'h0;
            eth_src_addr    <= 48'h0;
            frame_type      <= 15'h0;
            hw_type         <= 15'h0;
            prot_type       <= 15'h0;
            hw_len          <= 8'h0;
            prot_len        <= 8'h0;
            arp_op          <= 15'h0;
            arp_src_addr    <= 48'h0;
            arp_src_ip      <= 32'h0;
            arp_dest_addr   <= 48'h0;
            arp_dest_ip     <= 32'h0;

        end else begin
            case(state)
                `ETH_DEST_ADDR:
                     eth_dest_addr   <=  {eth_dest_addr[39:0], data_rx};
                `ETH_SRC_ADDR:
                     eth_src_addr    <=  {eth_src_addr[39:0], data_rx};
                `FRAME_TYPE:
                     frame_type      <=  {frame_type[7:0], data_rx};
                `HW_TYPE:
                     hw_type         <=  {hw_type[7:0], data_rx};
                `PROT_TYPE:
                     prot_type       <=  {prot_type[7:0], data_rx};
                `HW_LEN:
                     hw_len          <=  data_rx;
                `PROT_LEN:
                     prot_len        <=  data_rx;
                `ARP_OP:
                     arp_op          <=  {arp_op[7:0], data_rx};
                `ARP_SRC_ADDR:
                     arp_src_addr    <=  {arp_src_addr[39:0], data_rx};
                `ARP_SRC_IP:
                     arp_src_ip      <=  {arp_src_ip[23:0], data_rx};
                `ARP_DEST_ADDR:
                     arp_dest_addr   <=  {arp_dest_addr[39:0], data_rx};
                `ARP_DEST_IP:
                    arp_dest_ip     <=  {arp_dest_ip[23:0], data_rx};
                `END: begin
                    eth_dest_addr   <= eth_dest_addr;
                    eth_src_addr    <= eth_src_addr;
                    frame_type      <= frame_type;
                    hw_type         <= hw_type;
                    prot_type       <= prot_type;
                    hw_len          <= hw_len;        
                    prot_len        <= prot_len;      
                    arp_op          <= arp_op;
                    arp_src_addr    <= arp_src_addr;
                    arp_src_ip      <= arp_src_ip;
                    arp_dest_addr   <= arp_dest_addr;
                    arp_dest_ip     <= arp_dest_ip;
                end

                default: begin
                    eth_dest_addr   <= 48'h0;
                    eth_src_addr    <= 48'h0;
                    frame_type      <= 15'h0;
                    hw_type         <= 15'h0;
                    prot_type       <= 15'h0;
                    hw_len          <= 8'h0;
                    prot_len        <= 8'h0;
                    arp_op          <= 15'h0;
                    arp_src_addr    <= 48'h0;
                    arp_src_ip      <= 32'h0;
                    arp_dest_addr   <= 48'h0;
                    arp_dest_ip     <= 32'h0;
                end
            endcase
        end
    end


    //-- check data and drive outputs
    always @(state) begin
        if( (state          == `END)                &&
            (eth_dest_addr  == `BRDCAST_DEST_ADDR)   &&
            (frame_type     == `ARP_FRAME_TYPE)      &&
            (hw_type        == `ETH_HW_TYPE)         &&
            (prot_type      == `IP_PROT_TYPE)        &&
            (hw_len         == `ETH_HW_LEN)          &&
            (prot_len       == `IP_PROT_LEN)         &&
            (arp_op         == `REQ_ARP_OP)          &&
            (arp_dest_addr  == `ARP_REQ_ADDR)        &&
            (arp_dest_ip    == my_ip)               
          ) begin
              
            arp_send    <= 1'b1;
            source_mac  <= arp_src_addr;
            source_ip   <= arp_src_ip;
        end else begin
            arp_send    <= 1'b0;
            source_mac  <= 48'h0;
            source_ip   <= 31'h0;

        end
    end

endmodule

arp_response_block.v
//================================================================
// \ \/ /  _ \  |_   _| __ __ _  __| (_)_ __   __ _  
//  \  /| |_) |   | || '__/ _` |/ _` | | '_ \ / _` | 
//  /  \|  _ <    | || | | (_| | (_| | | | | | (_| | 
// /_/\_\_| \_\   |_||_|  \__,_|\__,_|_|_| |_|\__, | 
//                                            |___/  
//  _____ ____   ____    _     ____            _           _   
// |  ___|  _ \ / ___|  / \    |  _ \ _ __ ___ (_) ___  ___| |_ 
// | |_  | |_) | |  _  / _ \   | |_) | '__/ _ \| |/ _ \/ __| __|
// |  _| |  __/| |_| |/ ___ \  |  __/| | | (_) | |  __/ (__| |_ 
// |_|   |_|    \____/_/   \_\ |_|   |_|  \___// |\___|\___|\__|
//                                           |__/              
//Leela Pakanati
//ARP Response Design
//
//This is a module that recognizes a ARP request corresponding
//to its IP Address and repies with its MAC Address
//================================================================

module arp_response_block (
    input wire          ARESET,
    
    input wire [47:0]   MY_MAC,
    input wire [31:0]   MY_IPV4,

    input wire          CLK_RX,
    input wire          DATA_VALID_RX,
    input wire [7:0]    DATA_RX,

    input wire          CLK_TX,
    output wire         DATA_VALID_TX,
    output wire [7:0]   DATA_TX,
    input wire          DATA_ACK_TX
); 

    //buffers for asyc clock
    reg         arp_send;
    reg [47:0]  source_mac;
    reg [31:0]  source_ip;

    wire        arp_send_read;
    wire [47:0] source_mac_read;
    wire [31:0] source_ip_read;

    reg         sending;

    always @(posedge CLK_RX or posedge ARESET) begin
        if(ARESET)
            arp_send        <= 1'b0;
        else
            if(sending)
                arp_send    <= 1'b0;
            else
                arp_send    <= arp_send_read;
    end

    
    always @(posedge CLK_TX or ARESET) begin
        if(ARESET) begin
            source_mac      <= 48'h0;
            source_ip       <= 32'h0;
        end else begin
            if(arp_send_read) begin
                source_mac  <= source_mac_read;
                source_ip   <= source_ip_read;
            end else begin
                source_mac  <= source_mac;
                source_ip   <= source_ip;
            end
        end
    end

    always @(posedge CLK_TX or ARESET) begin
        if(ARESET)
            sending <= 1'b0;
        else 
            if(arp_send)
                sending <= 1'b1;
            else
                sending <= 1'b0;
    end

    input_det in0(
        .clk(CLK_RX),
        .areset(ARESET),
        .my_ip(MY_IPV4),
        .data_valid(DATA_VALID_RX),
        .data_rx(DATA_RX),

        .arp_send(arp_send_read),
        .source_mac(source_mac_read),
        .source_ip(source_ip_read)
    );

    output_MAC out0(
        .clk(CLK_TX),
        .data_valid(DATA_VALID_TX),
        .data_tx(DATA_TX),
        .data_ack_tx(DATA_ACK_TX),

        .send_mac(arp_send),
        .source_mac(source_mac),
        .source_ip(source_ip),
        .my_mac(MY_MAC),
        .my_ip(MY_IPV4)
    );

endmodule

test_benches/arp_response_block_tb.sv
`timescale 1ns / 1ps
//================================================================
// \ \/ /  _ \  |_   _| __ __ _  __| (_)_ __   __ _  
//  \  /| |_) |   | || '__/ _` |/ _` | | '_ \ / _` | 
//  /  \|  _ <    | || | | (_| | (_| | | | | | (_| | 
// /_/\_\_| \_\   |_||_|  \__,_|\__,_|_|_| |_|\__, | 
//                                            |___/  
//  _____ ____   ____    _     ____            _           _   
// |  ___|  _ \ / ___|  / \    |  _ \ _ __ ___ (_) ___  ___| |_ 
// | |_  | |_) | |  _  / _ \   | |_) | '__/ _ \| |/ _ \/ __| __|
// |  _| |  __/| |_| |/ ___ \  |  __/| | | (_) | |  __/ (__| |_ 
// |_|   |_|    \____/_/   \_\ |_|   |_|  \___// |\___|\___|\__|
//                                           |__/              
//Leela Pakanati
//arp_response_block -> Test arp_response_block module
//
//
//================================================================

module arp_response_block_tb();
    reg          ARESET;

    reg [47:0]   MY_MAC;
    reg [31:0]   MY_IPV4;

    reg          CLK_RX;
    reg          DATA_VALID_RX;
    reg [7:0]    DATA_RX;

    reg          CLK_TX;
    wire         DATA_VALID_TX;
    wire [7:0]   DATA_TX;
    reg          DATA_ACK_TX;

    arp_response_block arb0(
        .ARESET(ARESET),
        .MY_MAC(MY_MAC),
        .MY_IPV4(MY_IPV4),
                                       
        .CLK_RX(CLK_RX),
        .DATA_VALID_RX(DATA_VALID_RX),
        .DATA_RX(DATA_RX),
                                       
        .CLK_TX(CLK_TX),
        .DATA_VALID_TX(DATA_VALID_TX),
        .DATA_TX(DATA_TX),
        .DATA_ACK_TX(DATA_ACK_TX)
    );

    parameter [8*42-1:0] arp_request_block = 
        {
            //-- dest mac addr
            8'hff,
            8'hff,
            8'hff,
            8'hff,
            8'hff,
            8'hff,
            //-- source mac addr
            8'h00,
            8'h01,
            8'h42,
            8'h00,
            8'h5F,
            8'h68,
            //-- frame type
            8'h08,
            8'h06,
            //-- HW Type
            8'h00,
            8'h01,
            //-- Protocol Type
            8'h08,
            8'h00,
            //-- HW len
            8'h06,
            //-- Protocol len
            8'h04,
            //-- ARP Operation
            8'h00,
            8'h01,
            //-- source mac addr
            8'h00,
            8'h01,
            8'h42,
            8'h00,
            8'h5F,
            8'h68,
            //-- source ip addr
            8'hc0,
            8'ha8,
            8'h01,
            8'h01,
            //-- dest mac addr
            8'h00,
            8'h00,
            8'h00,
            8'h00,
            8'h00,
            8'h00,
            //-- dest ip addr
            8'hC0,
            8'hA8,
            8'h01,
            8'h02
        };


    initial begin
        $dumpfile("output_waveforms/arp_response_block_tb.vcd");
        $dumpvars(0, ARESET, MY_MAC, MY_IPV4, CLK_RX, DATA_VALID_RX, DATA_RX, CLK_TX, DATA_VALID_TX, DATA_TX, DATA_ACK_TX, arb0.arp_send, arb0.source_mac, arb0.source_ip);
    end


    initial
        $monitor("Time: %t, data_tx: %h, data_valid: %h, data_ack: %h", $time, DATA_TX, DATA_VALID_TX, DATA_ACK_TX);

    always begin
            #5;
            CLK_RX         <=  !CLK_RX;
            CLK_TX         <=  !CLK_TX;
    end

    initial begin
        ARESET          <= 1'b1;

        MY_IPV4         <= 32'hC0A80102;
        MY_MAC          <= 48'h000223010203;

        CLK_RX          <= 1'b0;
        DATA_VALID_RX   <= 8'h00;
        DATA_RX         <= 8'h00;

        #1;
        CLK_TX          <= 1'b0;
        DATA_VALID_RX   <= 8'h00;
        DATA_RX         <= 8'h00;
        DATA_ACK_TX     <= 1'b0;

        #9;

        #20;
        ARESET          <= 1'b0;
        #10;
        
        DATA_VALID_RX   <= 1'b1;
        for (int i =0; i<42; i=i+1) begin
            DATA_RX <= (arp_request_block >> (41-i)*8);
            #10;
        end

        DATA_VALID_RX   <= 1'b0;
        DATA_RX         <= 8'b0;

        #50;
        DATA_ACK_TX     <= 1'b1;
        #10;
        DATA_ACK_TX     <= 1'b0;
        #500;

        $stop;
        $finish;
    end


endmodule

output_waveforms/input_det_tb.vcd
$date
	Mon Oct 21 00:43:44 2019
$end
$version
	Icarus Verilog
$end
$timescale
	1ps
$end
$scope module arp_response_block_tb $end
$var reg 1 ! ARESET $end
$upscope $end
$scope module arp_response_block_tb $end
$var reg 48 " MY_MAC [47:0] $end
$upscope $end
$scope module arp_response_block_tb $end
$var reg 32 # MY_IPV4 [31:0] $end
$upscope $end
$scope module arp_response_block_tb $end
$var reg 1 $ CLK_RX $end
$upscope $end
$scope module arp_response_block_tb $end
$var reg 1 % DATA_VALID_RX $end
$upscope $end
$scope module arp_response_block_tb $end
$var reg 8 & DATA_RX [7:0] $end
$upscope $end
$scope module arp_response_block_tb $end
$var reg 1 ' CLK_TX $end
$upscope $end
$scope module arp_response_block_tb $end
$var wire 1 ( DATA_VALID_TX $end
$upscope $end
$scope module arp_response_block_tb $end
$var wire 8 ) DATA_TX [7:0] $end
$upscope $end
$scope module arp_response_block_tb $end
$var reg 1 * DATA_ACK_TX $end
$upscope $end
$enddefinitions $end
#0
$dumpvars
0*
bx )
x(
0'
b0 &
0%
0$
b11000000101010000000000100000010 #
b1000100011000000010000001000000011 "
1!
$end
#5000
b0 )
1(
1'
1$
#10000
0'
0$
#15000
0(
1'
1$
#20000
0'
0$
0!
#25000
1'
1$
#30000
0'
0$
b11111111 &
1%
#35000
1'
1$
#40000
0'
0$
#45000
1'
1$
#50000
0'
0$
#55000
1'
1$
#60000
0'
0$
#65000
1'
1$
#70000
0'
0$
#75000
1'
1$
#80000
0'
0$
#85000
1'
1$
#90000
0'
0$
b0 &
#95000
1'
1$
#100000
0'
0$
b1 &
#105000
1'
1$
#110000
0'
0$
b1000010 &
#115000
1'
1$
#120000
0'
0$
b0 &
#125000
1'
1$
#130000
0'
0$
b1011111 &
#135000
1'
1$
#140000
0'
0$
b1101000 &
#145000
1'
1$
#150000
0'
0$
b1000 &
#155000
1'
1$
#160000
0'
0$
b110 &
#165000
1'
1$
#170000
0'
0$
b0 &
#175000
1'
1$
#180000
0'
0$
b1 &
#185000
1'
1$
#190000
0'
0$
b1000 &
#195000
1'
1$
#200000
0'
0$
b0 &
#205000
1'
1$
#210000
0'
0$
b110 &
#215000
1'
1$
#220000
0'
0$
b100 &
#225000
1'
1$
#230000
0'
0$
b0 &
#235000
1'
1$
#240000
0'
0$
b1 &
#245000
1'
1$
#250000
0'
0$
b0 &
#255000
1'
1$
#260000
0'
0$
b1 &
#265000
1'
1$
#270000
0'
0$
b1000010 &
#275000
1'
1$
#280000
0'
0$
b0 &
#285000
1'
1$
#290000
0'
0$
b1011111 &
#295000
1'
1$
#300000
0'
0$
b1101000 &
#305000
1'
1$
#310000
0'
0$
b11000000 &
#315000
1'
1$
#320000
0'
0$
b10101000 &
#325000
1'
1$
#330000
0'
0$
b1 &
#335000
1'
1$
#340000
0'
0$
#345000
1'
1$
#350000
0'
0$
b0 &
#355000
1'
1$
#360000
0'
0$
#365000
1'
1$
#370000
0'
0$
#375000
1'
1$
#380000
0'
0$
#385000
1'
1$
#390000
0'
0$
#395000
1'
1$
#400000
0'
0$
#405000
1'
1$
#410000
0'
0$
b11000000 &
#415000
1'
1$
#420000
0'
0$
b10101000 &
#425000
1'
1$
#430000
0'
0$
b1 &
#435000
1'
1$
#440000
0'
0$
b10 &
#445000
1'
1$
#450000
0'
0$
b0 &
0%
#455000
1'
1$
#460000
0'
0$
#465000
1'
1$
#470000
0'
0$
#475000
1'
1$
#480000
0'
0$
#485000
1(
1'
1$
#490000
0'
0$
#495000
1'
1$
#500000
0'
0$
1*
#505000
1'
1$
#510000
0'
0$
0*
#515000
1'
1$
#520000
0'
0$
#525000
1'
1$
#530000
0'
0$
#535000
1'
1$
#540000
0'
0$
#545000
1'
1$
#550000
0'
0$
#555000
1'
1$
#560000
0'
0$
#565000
1'
1$
#570000
0'
0$
#575000
b10 )
1'
1$
#580000
0'
0$
#585000
b100011 )
1'
1$
#590000
0'
0$
#595000
b1 )
1'
1$
#600000
0'
0$
#605000
b10 )
1'
1$
#610000
0'
0$
#615000
b11 )
1'
1$
#620000
0'
0$
#625000
b1000 )
1'
1$
#630000
0'
0$
#635000
b110 )
1'
1$
#640000
0'
0$
#645000
b0 )
1'
1$
#650000
0'
0$
#655000
b1 )
1'
1$
#660000
0'
0$
#665000
b1000 )
1'
1$
#670000
0'
0$
#675000
b0 )
1'
1$
#680000
0'
0$
#685000
b110 )
1'
1$
#690000
0'
0$
#695000
b100 )
1'
1$
#700000
0'
0$
#705000
b0 )
1'
1$
#710000
0'
0$
#715000
b10 )
1'
1$
#720000
0'
0$
#725000
b0 )
1'
1$
#730000
0'
0$
#735000
b10 )
1'
1$
#740000
0'
0$
#745000
b100011 )
1'
1$
#750000
0'
0$
#755000
b1 )
1'
1$
#760000
0'
0$
#765000
b10 )
1'
1$
#770000
0'
0$
#775000
b11 )
1'
1$
#780000
0'
0$
#785000
b11000000 )
1'
1$
#790000
0'
0$
#795000
b10101000 )
1'
1$
#800000
0'
0$
#805000
b1 )
1'
1$
#810000
0'
0$
#815000
b10 )
1'
1$
#820000
0'
0$
#825000
b0 )
1'
1$
#830000
0'
0$
#835000
1'
1$
#840000
0'
0$
#845000
1'
1$
#850000
0'
0$
#855000
1'
1$
#860000
0'
0$
#865000
1'
1$
#870000
0'
0$
#875000
1'
1$
#880000
0'
0$
#885000
1'
1$
#890000
0'
0$
#895000
1'
1$
#900000
0'
0$
#905000
1'
1$
#910000
0'
0$
#915000
1'
1$
#920000
0'
0$
#925000
0(
1'
1$
